{
  "id": "pipeline/single-file",
  "title": "Single File Mode",
  "description": "Enable with useMultipleFiles: false.",
  "source": "@site/docs/pipeline/single-file.md",
  "sourceDirName": "pipeline",
  "slug": "/pipeline/single-file",
  "permalink": "/prisma-zod-generator/docs/pipeline/single-file",
  "draft": false,
  "unlisted": false,
  "editUrl": "https://github.com/omar-dulaimi/prisma-zod-generator/tree/master/website/docs/pipeline/single-file.md",
  "tags": [],
  "version": "current",
  "lastUpdatedAt": 1539502055000,
  "frontMatter": {
    "id": "single-file",
    "title": "Single File Mode"
  },
  "sidebar": "docs",
  "previous": {
    "title": "Pure Model Schemas",
    "permalink": "/prisma-zod-generator/docs/pipeline/pure-models"
  },
  "next": {
    "title": "Special Type Mapping",
    "permalink": "/prisma-zod-generator/docs/pipeline/special-types"
  }
}